{
  "levelId": "D02_S03",
  "difficulty": 2,
  "spawns": [
    {
      "time": 0,
      "position": {
        "x": 1.4,
        "y": 0.2222,
        "z": 0
      },
      "positionRandomRange": {
        "x": 0.25,
        "y": 0.4444,
        "z": 0
      },
      "enemyTypeId": "Mosquito",
      "count": 13,
      "interval": 1.04
    },
    {
      "time": 6.1,
      "position": {
        "x": 1.5,
        "y": 0.3333,
        "z": 0
      },
      "positionRandomRange": {
        "x": 0.225,
        "y": 0.3556,
        "z": 0
      },
      "enemyTypeId": "Fly",
      "count": 50,
      "interval": 0.5
    },
    {
      "time": 3.1,
      "position": {
        "x": -0.3,
        "y": 0.3333,
        "z": 0
      },
      "positionRandomRange": {
        "x": 0.225,
        "y": 0.3556,
        "z": 0
      },
      "enemyTypeId": "Fly",
      "count": 50,
      "interval": 0.5
    }
  ],
  "useSpawnBounds": true,
  "spawnBoundsMin": {
    "x": -1.0,
    "y": -1.3333
  },
  "spawnBoundsMax": {
    "x": 2.0,
    "y": 1.5556
  },
  "useNormalizedCoordinates": true
}
